appframe/__init__.py
appframe/__main__.py
appframe/application.py
appframe/command.py
appframe/log.py
appframe/main.py
appframe/singleton.py
appframe/version.py
test-app/__main__.py
test-app/commands/greet.py
test-app/commands/run.py
test-app/features/test1.py
tests/test_version.py
appframe-0.0.1.dist-info/LICENSE
appframe-0.0.1.dist-info/METADATA
appframe-0.0.1.dist-info/WHEEL
appframe-0.0.1.dist-info/entry_points.txt
appframe-0.0.1.dist-info/top_level.txt
appframe-0.0.1.dist-info/RECORD
