Metadata-Version: 2.1
Name: appframe
Version: 0.0.1
Summary: A Python Application Development Framework
Home-page: https://github.com/webplane/appframe
Author: João Pinto
Author-email: lamego.pinto@gmail.com
License: MIT
Platform: UNKNOWN
